pulumi_cloudamqp/__init__.py
pulumi_cloudamqp/_inputs.py
pulumi_cloudamqp/_utilities.py
pulumi_cloudamqp/account_actions.py
pulumi_cloudamqp/alarm.py
pulumi_cloudamqp/custom_certificate.py
pulumi_cloudamqp/custom_domain.py
pulumi_cloudamqp/extra_disk_size.py
pulumi_cloudamqp/get_account.py
pulumi_cloudamqp/get_account_vpcs.py
pulumi_cloudamqp/get_alarm.py
pulumi_cloudamqp/get_alarms.py
pulumi_cloudamqp/get_credentials.py
pulumi_cloudamqp/get_instance.py
pulumi_cloudamqp/get_nodes.py
pulumi_cloudamqp/get_notification.py
pulumi_cloudamqp/get_notifications.py
pulumi_cloudamqp/get_plugins.py
pulumi_cloudamqp/get_plugins_community.py
pulumi_cloudamqp/get_upgradable_versions.py
pulumi_cloudamqp/get_vpc_gcp_info.py
pulumi_cloudamqp/get_vpc_info.py
pulumi_cloudamqp/instance.py
pulumi_cloudamqp/integration_aws_eventbridge.py
pulumi_cloudamqp/integration_log.py
pulumi_cloudamqp/integration_metric.py
pulumi_cloudamqp/integration_metric_prometheus.py
pulumi_cloudamqp/maintenance_window.py
pulumi_cloudamqp/node_actions.py
pulumi_cloudamqp/notification.py
pulumi_cloudamqp/oauth2_configuration.py
pulumi_cloudamqp/outputs.py
pulumi_cloudamqp/plugin.py
pulumi_cloudamqp/plugin_community.py
pulumi_cloudamqp/privatelink_aws.py
pulumi_cloudamqp/privatelink_azure.py
pulumi_cloudamqp/provider.py
pulumi_cloudamqp/pulumi-plugin.json
pulumi_cloudamqp/py.typed
pulumi_cloudamqp/rabbit_configuration.py
pulumi_cloudamqp/security_firewall.py
pulumi_cloudamqp/trust_store.py
pulumi_cloudamqp/upgrade_lavinmq.py
pulumi_cloudamqp/upgrade_rabbitmq.py
pulumi_cloudamqp/vpc.py
pulumi_cloudamqp/vpc_connect.py
pulumi_cloudamqp/vpc_gcp_peering.py
pulumi_cloudamqp/vpc_peering.py
pulumi_cloudamqp/webhook.py
pulumi_cloudamqp/config/__init__.py
pulumi_cloudamqp/config/__init__.pyi
pulumi_cloudamqp/config/vars.py
pulumi_cloudamqp-3.25.1.dist-info/METADATA
pulumi_cloudamqp-3.25.1.dist-info/WHEEL
pulumi_cloudamqp-3.25.1.dist-info/top_level.txt
pulumi_cloudamqp-3.25.1.dist-info/RECORD
